blog_uploader/__init__.py
blog_uploader/main.py
blog_uploader-0.1.7.dist-info/METADATA
blog_uploader-0.1.7.dist-info/WHEEL
blog_uploader-0.1.7.dist-info/entry_points.txt
blog_uploader-0.1.7.dist-info/top_level.txt
blog_uploader-0.1.7.dist-info/RECORD
