Metadata-Version: 2.1
Name: blog-uploader
Version: 0.1.7
Summary: A command-line tool to manage Hugo blog posts.
Home-page: https://github.com/your-username/blog-uploader
Author: Your Name
Author-email: your.email@example.com
Classifier: Programming Language :: Python :: 3
Classifier: License :: OSI Approved :: MIT License
Classifier: Operating System :: OS Independent
Requires-Python: >=3.6
Requires-Dist: GitPython
Requires-Dist: click
Requires-Dist: rich
Requires-Dist: python-frontmatter
Requires-Dist: requests
Requires-Dist: pycryptodome
Requires-Dist: mistune
